nerfprobe/__init__.py
nerfprobe/cli.py
nerfprobe/runner.py
nerfprobe/gateways/__init__.py
nerfprobe/gateways/anthropic.py
nerfprobe/gateways/bedrock.py
nerfprobe/gateways/dashscope.py
nerfprobe/gateways/google.py
nerfprobe/gateways/ollama.py
nerfprobe/gateways/openai_compat.py
nerfprobe/gateways/zhipu.py
nerfprobe-0.2.0.dist-info/METADATA
nerfprobe-0.2.0.dist-info/WHEEL
nerfprobe-0.2.0.dist-info/entry_points.txt
nerfprobe-0.2.0.dist-info/licenses/LICENSE
nerfprobe-0.2.0.dist-info/RECORD
