Metadata-Version: 2.4
Name: nerfprobe
Version: 0.2.0
Summary: Scientifically-grounded LLM degradation detection for developers
Author-email: Stefan Wiest <skew202@gmail.com>
License-Expression: Apache-2.0
License-File: LICENSE
Keywords: degradation,inference,llm,probes,quantization,testing
Classifier: Development Status :: 4 - Beta
Classifier: Intended Audience :: Developers
Classifier: License :: OSI Approved :: Apache Software License
Classifier: Programming Language :: Python :: 3.11
Classifier: Programming Language :: Python :: 3.12
Classifier: Topic :: Scientific/Engineering :: Artificial Intelligence
Classifier: Topic :: Software Development :: Testing
Requires-Python: >=3.11
Requires-Dist: httpx>=0.27.0
Requires-Dist: nerfprobe-core>=0.2.0
Requires-Dist: rich>=13.0.0
Requires-Dist: typer>=0.12.0
Provides-Extra: dev
Requires-Dist: mypy>=1.14.0; extra == 'dev'
Requires-Dist: pytest-asyncio>=0.24.0; extra == 'dev'
Requires-Dist: pytest>=8.0.0; extra == 'dev'
Requires-Dist: respx>=0.22.0; extra == 'dev'
Requires-Dist: ruff>=0.8.0; extra == 'dev'
